{
  "kind": "collectionType",
  "collectionName": "events",
  "info": {
    "singularName": "event",
    "pluralName": "events",
    "displayName": "event"
  },
  "options": {
    "draftAndPublish": true
  },
  "pluginOptions": {},
  "attributes": {
    "Titel": {
      "type": "string"
    },
    "Slug": {
      "type": "uid",
      "targetField": "Titel"
    },
    "Date": {
      "type": "date"
    },
    "BtnText": {
      "type": "string"
    },
    "EventSneakCover": {
      "allowedTypes": [
        "images",
        "files",
        "videos",
        "audios"
      ],
      "type": "media",
      "multiple": false
    },
    "PageCover": {
      "allowedTypes": [
        "images",
        "files",
        "videos",
        "audios"
      ],
      "type": "media",
      "multiple": false
    }
  }
}
